todo/__init__.py
todo/__main__.py
todo/add.py
todo/delete.py
todo/edit.py
todo/globals.py
todo9-0.0.1.dist-info/LICENSE
todo9-0.0.1.dist-info/METADATA
todo9-0.0.1.dist-info/WHEEL
todo9-0.0.1.dist-info/entry_points.txt
todo9-0.0.1.dist-info/top_level.txt
todo9-0.0.1.dist-info/RECORD
